ewatercycle_marrmot/__init__.py
ewatercycle_marrmot/forcing.py
ewatercycle_marrmot/forcing_diagnostic_script.py
ewatercycle_marrmot/model.py
ewatercycle_marrmot-0.0.2.dist-info/METADATA
ewatercycle_marrmot-0.0.2.dist-info/WHEEL
ewatercycle_marrmot-0.0.2.dist-info/entry_points.txt
ewatercycle_marrmot-0.0.2.dist-info/licenses/LICENSE.txt
ewatercycle_marrmot-0.0.2.dist-info/RECORD
